scrape_amazon/__init__.py
scrape_amazon/cli.py
scrape_amazon/scraper.py
scrape_amazon/util/__init__.py
scrape_amazon/util/scrape.py
scrape_amazon/util/urlFunctions.py
scrape_amazon-0.1.8.dist-info/LICENSE
scrape_amazon-0.1.8.dist-info/METADATA
scrape_amazon-0.1.8.dist-info/WHEEL
scrape_amazon-0.1.8.dist-info/entry_points.txt
scrape_amazon-0.1.8.dist-info/top_level.txt
scrape_amazon-0.1.8.dist-info/RECORD
