Metadata-Version: 2.1
Name: scrape-amazon
Version: 0.1.8
Summary: Scrape Amazon Reviews
Home-page: http://github.com/officialpm/scrape-amazon
Author: Parth Maniar
Author-email: officialparthmaniar@gmail.com
License: MIT
Download-URL: https://pypi.org/project/scrape-amazon
Project-URL: Documentation, https://github.com/officialpm/scrape-amazon
Project-URL: Code, https://github.com/officialpm/scrape-amazon
Project-URL: Issue tracker, https://github.com/officialpm/scrape-amazon/issues
Keywords: Amazon,Scrape,Reviews,Scraper,Products
Platform: UNKNOWN
Classifier: Operating System :: OS Independent
Classifier: Intended Audience :: Developers
Classifier: Topic :: Utilities
Classifier: Natural Language :: English
Classifier: Programming Language :: Python :: 3
Classifier: Programming Language :: Python :: 3.6
Classifier: Programming Language :: Python :: 3.7
Classifier: Programming Language :: Python :: 3.8
Classifier: Programming Language :: Python :: 3 :: Only
Requires-Python: >=3.6
Requires-Dist: beautifulsoup4
Requires-Dist: pandas
Requires-Dist: p-tqdm
Requires-Dist: my-fake-useragent
Requires-Dist: requests
Requires-Dist: datefinder
